{"nodes": [{"id": "home_pc051_\u0440\u0430\u0437\u0440\u0430\u0431\u043e\u0442\u043a\u0430_\u0440\u0430\u0431\u043e\u0442\u0430_parsevk_docs_superpowers_specs_2026_05_07_tasks_service_migration_design_md", "label": "2026-05-07-tasks-service-migration-design.md", "file_type": "document", "source_file": "docs/superpowers/specs/2026-05-07-tasks-service-migration-design.md", "source_location": "L1"}, {"id": "home_pc051_\u0440\u0430\u0437\u0440\u0430\u0431\u043e\u0442\u043a\u0430_\u0440\u0430\u0431\u043e\u0442\u0430_parsevk_docs_superpowers_specs_2026_05_07_tasks_service_migration_design_tasks_service_migration_design", "label": "Tasks Service Migration Design", "file_type": "document", "source_file": "docs/superpowers/specs/2026-05-07-tasks-service-migration-design.md", "source_location": "L1"}, {"id": "home_pc051_\u0440\u0430\u0437\u0440\u0430\u0431\u043e\u0442\u043a\u0430_\u0440\u0430\u0431\u043e\u0442\u0430_parsevk_docs_superpowers_specs_2026_05_07_tasks_service_migration_design_\u043a\u043e\u043d\u0442\u0435\u043a\u0441\u0442", "label": "\u041a\u043e\u043d\u0442\u0435\u043a\u0441\u0442", "file_type": "document", "source_file": "docs/superpowers/specs/2026-05-07-tasks-service-migration-design.md", "source_location": "L3"}, {"id": "home_pc051_\u0440\u0430\u0437\u0440\u0430\u0431\u043e\u0442\u043a\u0430_\u0440\u0430\u0431\u043e\u0442\u0430_parsevk_docs_superpowers_specs_2026_05_07_tasks_service_migration_design_\u0446\u0435\u043b\u044c", "label": "\u0426\u0435\u043b\u044c", "file_type": "document", "source_file": "docs/superpowers/specs/2026-05-07-tasks-service-migration-design.md", "source_location": "L24"}, {"id": "home_pc051_\u0440\u0430\u0437\u0440\u0430\u0431\u043e\u0442\u043a\u0430_\u0440\u0430\u0431\u043e\u0442\u0430_parsevk_docs_superpowers_specs_2026_05_07_tasks_service_migration_design_\u043d\u0435_\u0432\u0445\u043e\u0434\u0438\u0442_\u0432_\u044d\u0442\u0430\u043f", "label": "\u041d\u0435 \u0432\u0445\u043e\u0434\u0438\u0442 \u0432 \u044d\u0442\u0430\u043f", "file_type": "document", "source_file": "docs/superpowers/specs/2026-05-07-tasks-service-migration-design.md", "source_location": "L38"}, {"id": "home_pc051_\u0440\u0430\u0437\u0440\u0430\u0431\u043e\u0442\u043a\u0430_\u0440\u0430\u0431\u043e\u0442\u0430_parsevk_docs_superpowers_specs_2026_05_07_tasks_service_migration_design_\u0440\u0430\u0441\u0441\u043c\u043e\u0442\u0440\u0435\u043d\u043d\u044b\u0435_\u043f\u043e\u0434\u0445\u043e\u0434\u044b", "label": "\u0420\u0430\u0441\u0441\u043c\u043e\u0442\u0440\u0435\u043d\u043d\u044b\u0435 \u043f\u043e\u0434\u0445\u043e\u0434\u044b", "file_type": "document", "source_file": "docs/superpowers/specs/2026-05-07-tasks-service-migration-design.md", "source_location": "L50"}, {"id": "home_pc051_\u0440\u0430\u0437\u0440\u0430\u0431\u043e\u0442\u043a\u0430_\u0440\u0430\u0431\u043e\u0442\u0430_parsevk_docs_superpowers_specs_2026_05_07_tasks_service_migration_design_\u043f\u043e\u0434\u0445\u043e\u0434_a_tasks_service_\u0432\u043b\u0430\u0434\u0435\u0435\u0442_\u0437\u0430\u0434\u0430\u0447\u0430\u043c\u0438_execution_\u043f\u043e\u0437\u0436\u0435", "label": "\u041f\u043e\u0434\u0445\u043e\u0434 A: tasks-service \u0432\u043b\u0430\u0434\u0435\u0435\u0442 \u0437\u0430\u0434\u0430\u0447\u0430\u043c\u0438, execution \u043f\u043e\u0437\u0436\u0435", "file_type": "document", "source_file": "docs/superpowers/specs/2026-05-07-tasks-service-migration-design.md", "source_location": "L52"}, {"id": "home_pc051_\u0440\u0430\u0437\u0440\u0430\u0431\u043e\u0442\u043a\u0430_\u0440\u0430\u0431\u043e\u0442\u0430_parsevk_docs_superpowers_specs_2026_05_07_tasks_service_migration_design_\u043f\u043e\u0434\u0445\u043e\u0434_b_tasks_service_\u0432\u044b\u0437\u044b\u0432\u0430\u0435\u0442_\u0441\u0442\u0430\u0440\u044b\u0439_nestjs_api", "label": "\u041f\u043e\u0434\u0445\u043e\u0434 B: tasks-service \u0432\u044b\u0437\u044b\u0432\u0430\u0435\u0442 \u0441\u0442\u0430\u0440\u044b\u0439 NestJS API", "file_type": "document", "source_file": "docs/superpowers/specs/2026-05-07-tasks-service-migration-design.md", "source_location": "L61"}, {"id": "home_pc051_\u0440\u0430\u0437\u0440\u0430\u0431\u043e\u0442\u043a\u0430_\u0440\u0430\u0431\u043e\u0442\u0430_parsevk_docs_superpowers_specs_2026_05_07_tasks_service_migration_design_\u043f\u043e\u0434\u0445\u043e\u0434_c_\u043f\u0435\u0440\u0435\u043d\u043e\u0441_tasks_\u0438_vk_worker_\u0432\u043c\u0435\u0441\u0442\u0435", "label": "\u041f\u043e\u0434\u0445\u043e\u0434 C: \u043f\u0435\u0440\u0435\u043d\u043e\u0441 tasks \u0438 VK worker \u0432\u043c\u0435\u0441\u0442\u0435", "file_type": "document", "source_file": "docs/superpowers/specs/2026-05-07-tasks-service-migration-design.md", "source_location": "L67"}, {"id": "home_pc051_\u0440\u0430\u0437\u0440\u0430\u0431\u043e\u0442\u043a\u0430_\u0440\u0430\u0431\u043e\u0442\u0430_parsevk_docs_superpowers_specs_2026_05_07_tasks_service_migration_design_\u0430\u0440\u0445\u0438\u0442\u0435\u043a\u0442\u0443\u0440\u0430", "label": "\u0410\u0440\u0445\u0438\u0442\u0435\u043a\u0442\u0443\u0440\u0430", "file_type": "document", "source_file": "docs/superpowers/specs/2026-05-07-tasks-service-migration-design.md", "source_location": "L73"}, {"id": "home_pc051_\u0440\u0430\u0437\u0440\u0430\u0431\u043e\u0442\u043a\u0430_\u0440\u0430\u0431\u043e\u0442\u0430_parsevk_docs_superpowers_specs_2026_05_07_tasks_service_migration_design_\u0434\u0430\u043d\u043d\u044b\u0435", "label": "\u0414\u0430\u043d\u043d\u044b\u0435", "file_type": "document", "source_file": "docs/superpowers/specs/2026-05-07-tasks-service-migration-design.md", "source_location": "L120"}, {"id": "home_pc051_\u0440\u0430\u0437\u0440\u0430\u0431\u043e\u0442\u043a\u0430_\u0440\u0430\u0431\u043e\u0442\u0430_parsevk_docs_superpowers_specs_2026_05_07_tasks_service_migration_design_tasks", "label": "`tasks`", "file_type": "document", "source_file": "docs/superpowers/specs/2026-05-07-tasks-service-migration-design.md", "source_location": "L125"}, {"id": "home_pc051_\u0440\u0430\u0437\u0440\u0430\u0431\u043e\u0442\u043a\u0430_\u0440\u0430\u0431\u043e\u0442\u0430_parsevk_docs_superpowers_specs_2026_05_07_tasks_service_migration_design_task_audit_logs", "label": "`task_audit_logs`", "file_type": "document", "source_file": "docs/superpowers/specs/2026-05-07-tasks-service-migration-design.md", "source_location": "L183"}, {"id": "home_pc051_\u0440\u0430\u0437\u0440\u0430\u0431\u043e\u0442\u043a\u0430_\u0440\u0430\u0431\u043e\u0442\u0430_parsevk_docs_superpowers_specs_2026_05_07_tasks_service_migration_design_task_automation_settings", "label": "`task_automation_settings`", "file_type": "document", "source_file": "docs/superpowers/specs/2026-05-07-tasks-service-migration-design.md", "source_location": "L226"}, {"id": "home_pc051_\u0440\u0430\u0437\u0440\u0430\u0431\u043e\u0442\u043a\u0430_\u0440\u0430\u0431\u043e\u0442\u0430_parsevk_docs_superpowers_specs_2026_05_07_tasks_service_migration_design_outbox_events", "label": "`outbox_events`", "file_type": "document", "source_file": "docs/superpowers/specs/2026-05-07-tasks-service-migration-design.md", "source_location": "L257"}, {"id": "home_pc051_\u0440\u0430\u0437\u0440\u0430\u0431\u043e\u0442\u043a\u0430_\u0440\u0430\u0431\u043e\u0442\u0430_parsevk_docs_superpowers_specs_2026_05_07_tasks_service_migration_design_api_contract", "label": "API Contract", "file_type": "document", "source_file": "docs/superpowers/specs/2026-05-07-tasks-service-migration-design.md", "source_location": "L287"}, {"id": "home_pc051_\u0440\u0430\u0437\u0440\u0430\u0431\u043e\u0442\u043a\u0430_\u0440\u0430\u0431\u043e\u0442\u0430_parsevk_docs_superpowers_specs_2026_05_07_tasks_service_migration_design_behavior", "label": "Behavior", "file_type": "document", "source_file": "docs/superpowers/specs/2026-05-07-tasks-service-migration-design.md", "source_location": "L398"}, {"id": "home_pc051_\u0440\u0430\u0437\u0440\u0430\u0431\u043e\u0442\u043a\u0430_\u0440\u0430\u0431\u043e\u0442\u0430_parsevk_docs_superpowers_specs_2026_05_07_tasks_service_migration_design_create_parse_task", "label": "Create Parse Task", "file_type": "document", "source_file": "docs/superpowers/specs/2026-05-07-tasks-service-migration-design.md", "source_location": "L400"}, {"id": "home_pc051_\u0440\u0430\u0437\u0440\u0430\u0431\u043e\u0442\u043a\u0430_\u0440\u0430\u0431\u043e\u0442\u0430_parsevk_docs_superpowers_specs_2026_05_07_tasks_service_migration_design_resume", "label": "Resume", "file_type": "document", "source_file": "docs/superpowers/specs/2026-05-07-tasks-service-migration-design.md", "source_location": "L413"}, {"id": "home_pc051_\u0440\u0430\u0437\u0440\u0430\u0431\u043e\u0442\u043a\u0430_\u0440\u0430\u0431\u043e\u0442\u0430_parsevk_docs_superpowers_specs_2026_05_07_tasks_service_migration_design_check", "label": "Check", "file_type": "document", "source_file": "docs/superpowers/specs/2026-05-07-tasks-service-migration-design.md", "source_location": "L424"}, {"id": "home_pc051_\u0440\u0430\u0437\u0440\u0430\u0431\u043e\u0442\u043a\u0430_\u0440\u0430\u0431\u043e\u0442\u0430_parsevk_docs_superpowers_specs_2026_05_07_tasks_service_migration_design_delete", "label": "Delete", "file_type": "document", "source_file": "docs/superpowers/specs/2026-05-07-tasks-service-migration-design.md", "source_location": "L435"}, {"id": "home_pc051_\u0440\u0430\u0437\u0440\u0430\u0431\u043e\u0442\u043a\u0430_\u0440\u0430\u0431\u043e\u0442\u0430_parsevk_docs_superpowers_specs_2026_05_07_tasks_service_migration_design_automation_settings", "label": "Automation Settings", "file_type": "document", "source_file": "docs/superpowers/specs/2026-05-07-tasks-service-migration-design.md", "source_location": "L451"}, {"id": "home_pc051_\u0440\u0430\u0437\u0440\u0430\u0431\u043e\u0442\u043a\u0430_\u0440\u0430\u0431\u043e\u0442\u0430_parsevk_docs_superpowers_specs_2026_05_07_tasks_service_migration_design_automation_run", "label": "Automation Run", "file_type": "document", "source_file": "docs/superpowers/specs/2026-05-07-tasks-service-migration-design.md", "source_location": "L494"}, {"id": "home_pc051_\u0440\u0430\u0437\u0440\u0430\u0431\u043e\u0442\u043a\u0430_\u0440\u0430\u0431\u043e\u0442\u0430_parsevk_docs_superpowers_specs_2026_05_07_tasks_service_migration_design_gateway_responsibilities", "label": "Gateway Responsibilities", "file_type": "document", "source_file": "docs/superpowers/specs/2026-05-07-tasks-service-migration-design.md", "source_location": "L551"}, {"id": "home_pc051_\u0440\u0430\u0437\u0440\u0430\u0431\u043e\u0442\u043a\u0430_\u0440\u0430\u0431\u043e\u0442\u0430_parsevk_docs_superpowers_specs_2026_05_07_tasks_service_migration_design_frontend_migration", "label": "Frontend Migration", "file_type": "document", "source_file": "docs/superpowers/specs/2026-05-07-tasks-service-migration-design.md", "source_location": "L565"}, {"id": "home_pc051_\u0440\u0430\u0437\u0440\u0430\u0431\u043e\u0442\u043a\u0430_\u0440\u0430\u0431\u043e\u0442\u0430_parsevk_docs_superpowers_specs_2026_05_07_tasks_service_migration_design_events", "label": "Events", "file_type": "document", "source_file": "docs/superpowers/specs/2026-05-07-tasks-service-migration-design.md", "source_location": "L576"}, {"id": "home_pc051_\u0440\u0430\u0437\u0440\u0430\u0431\u043e\u0442\u043a\u0430_\u0440\u0430\u0431\u043e\u0442\u0430_parsevk_docs_superpowers_specs_2026_05_07_tasks_service_migration_design_testing", "label": "Testing", "file_type": "document", "source_file": "docs/superpowers/specs/2026-05-07-tasks-service-migration-design.md", "source_location": "L604"}, {"id": "home_pc051_\u0440\u0430\u0437\u0440\u0430\u0431\u043e\u0442\u043a\u0430_\u0440\u0430\u0431\u043e\u0442\u0430_parsevk_docs_superpowers_specs_2026_05_07_tasks_service_migration_design_rollout", "label": "Rollout", "file_type": "document", "source_file": "docs/superpowers/specs/2026-05-07-tasks-service-migration-design.md", "source_location": "L648"}, {"id": "home_pc051_\u0440\u0430\u0437\u0440\u0430\u0431\u043e\u0442\u043a\u0430_\u0440\u0430\u0431\u043e\u0442\u0430_parsevk_docs_superpowers_specs_2026_05_07_tasks_service_migration_design_risks", "label": "Risks", "file_type": "document", "source_file": "docs/superpowers/specs/2026-05-07-tasks-service-migration-design.md", "source_location": "L659"}, {"id": "home_pc051_\u0440\u0430\u0437\u0440\u0430\u0431\u043e\u0442\u043a\u0430_\u0440\u0430\u0431\u043e\u0442\u0430_parsevk_docs_superpowers_specs_2026_05_07_tasks_service_migration_design_resolved_decisions", "label": "Resolved Decisions", "file_type": "document", "source_file": "docs/superpowers/specs/2026-05-07-tasks-service-migration-design.md", "source_location": "L674"}], "edges": [{"source": "home_pc051_\u0440\u0430\u0437\u0440\u0430\u0431\u043e\u0442\u043a\u0430_\u0440\u0430\u0431\u043e\u0442\u0430_parsevk_docs_superpowers_specs_2026_05_07_tasks_service_migration_design_md", "target": "home_pc051_\u0440\u0430\u0437\u0440\u0430\u0431\u043e\u0442\u043a\u0430_\u0440\u0430\u0431\u043e\u0442\u0430_parsevk_docs_superpowers_specs_2026_05_07_tasks_service_migration_design_tasks_service_migration_design", "relation": "contains", "confidence": "EXTRACTED", "source_file": "docs/superpowers/specs/2026-05-07-tasks-service-migration-design.md", "source_location": "L1", "weight": 1.0}, {"source": "home_pc051_\u0440\u0430\u0437\u0440\u0430\u0431\u043e\u0442\u043a\u0430_\u0440\u0430\u0431\u043e\u0442\u0430_parsevk_docs_superpowers_specs_2026_05_07_tasks_service_migration_design_tasks_service_migration_design", "target": "home_pc051_\u0440\u0430\u0437\u0440\u0430\u0431\u043e\u0442\u043a\u0430_\u0440\u0430\u0431\u043e\u0442\u0430_parsevk_docs_superpowers_specs_2026_05_07_tasks_service_migration_design_\u043a\u043e\u043d\u0442\u0435\u043a\u0441\u0442", "relation": "contains", "confidence": "EXTRACTED", "source_file": "docs/superpowers/specs/2026-05-07-tasks-service-migration-design.md", "source_location": "L3", "weight": 1.0}, {"source": "home_pc051_\u0440\u0430\u0437\u0440\u0430\u0431\u043e\u0442\u043a\u0430_\u0440\u0430\u0431\u043e\u0442\u0430_parsevk_docs_superpowers_specs_2026_05_07_tasks_service_migration_design_tasks_service_migration_design", "target": "home_pc051_\u0440\u0430\u0437\u0440\u0430\u0431\u043e\u0442\u043a\u0430_\u0440\u0430\u0431\u043e\u0442\u0430_parsevk_docs_superpowers_specs_2026_05_07_tasks_service_migration_design_\u0446\u0435\u043b\u044c", "relation": "contains", "confidence": "EXTRACTED", "source_file": "docs/superpowers/specs/2026-05-07-tasks-service-migration-design.md", "source_location": "L24", "weight": 1.0}, {"source": "home_pc051_\u0440\u0430\u0437\u0440\u0430\u0431\u043e\u0442\u043a\u0430_\u0440\u0430\u0431\u043e\u0442\u0430_parsevk_docs_superpowers_specs_2026_05_07_tasks_service_migration_design_tasks_service_migration_design", "target": "home_pc051_\u0440\u0430\u0437\u0440\u0430\u0431\u043e\u0442\u043a\u0430_\u0440\u0430\u0431\u043e\u0442\u0430_parsevk_docs_superpowers_specs_2026_05_07_tasks_service_migration_design_\u043d\u0435_\u0432\u0445\u043e\u0434\u0438\u0442_\u0432_\u044d\u0442\u0430\u043f", "relation": "contains", "confidence": "EXTRACTED", "source_file": "docs/superpowers/specs/2026-05-07-tasks-service-migration-design.md", "source_location": "L38", "weight": 1.0}, {"source": "home_pc051_\u0440\u0430\u0437\u0440\u0430\u0431\u043e\u0442\u043a\u0430_\u0440\u0430\u0431\u043e\u0442\u0430_parsevk_docs_superpowers_specs_2026_05_07_tasks_service_migration_design_tasks_service_migration_design", "target": "home_pc051_\u0440\u0430\u0437\u0440\u0430\u0431\u043e\u0442\u043a\u0430_\u0440\u0430\u0431\u043e\u0442\u0430_parsevk_docs_superpowers_specs_2026_05_07_tasks_service_migration_design_\u0440\u0430\u0441\u0441\u043c\u043e\u0442\u0440\u0435\u043d\u043d\u044b\u0435_\u043f\u043e\u0434\u0445\u043e\u0434\u044b", "relation": "contains", "confidence": "EXTRACTED", "source_file": "docs/superpowers/specs/2026-05-07-tasks-service-migration-design.md", "source_location": "L50", "weight": 1.0}, {"source": "home_pc051_\u0440\u0430\u0437\u0440\u0430\u0431\u043e\u0442\u043a\u0430_\u0440\u0430\u0431\u043e\u0442\u0430_parsevk_docs_superpowers_specs_2026_05_07_tasks_service_migration_design_\u0440\u0430\u0441\u0441\u043c\u043e\u0442\u0440\u0435\u043d\u043d\u044b\u0435_\u043f\u043e\u0434\u0445\u043e\u0434\u044b", "target": "home_pc051_\u0440\u0430\u0437\u0440\u0430\u0431\u043e\u0442\u043a\u0430_\u0440\u0430\u0431\u043e\u0442\u0430_parsevk_docs_superpowers_specs_2026_05_07_tasks_service_migration_design_\u043f\u043e\u0434\u0445\u043e\u0434_a_tasks_service_\u0432\u043b\u0430\u0434\u0435\u0435\u0442_\u0437\u0430\u0434\u0430\u0447\u0430\u043c\u0438_execution_\u043f\u043e\u0437\u0436\u0435", "relation": "contains", "confidence": "EXTRACTED", "source_file": "docs/superpowers/specs/2026-05-07-tasks-service-migration-design.md", "source_location": "L52", "weight": 1.0}, {"source": "home_pc051_\u0440\u0430\u0437\u0440\u0430\u0431\u043e\u0442\u043a\u0430_\u0440\u0430\u0431\u043e\u0442\u0430_parsevk_docs_superpowers_specs_2026_05_07_tasks_service_migration_design_\u0440\u0430\u0441\u0441\u043c\u043e\u0442\u0440\u0435\u043d\u043d\u044b\u0435_\u043f\u043e\u0434\u0445\u043e\u0434\u044b", "target": "home_pc051_\u0440\u0430\u0437\u0440\u0430\u0431\u043e\u0442\u043a\u0430_\u0440\u0430\u0431\u043e\u0442\u0430_parsevk_docs_superpowers_specs_2026_05_07_tasks_service_migration_design_\u043f\u043e\u0434\u0445\u043e\u0434_b_tasks_service_\u0432\u044b\u0437\u044b\u0432\u0430\u0435\u0442_\u0441\u0442\u0430\u0440\u044b\u0439_nestjs_api", "relation": "contains", "confidence": "EXTRACTED", "source_file": "docs/superpowers/specs/2026-05-07-tasks-service-migration-design.md", "source_location": "L61", "weight": 1.0}, {"source": "home_pc051_\u0440\u0430\u0437\u0440\u0430\u0431\u043e\u0442\u043a\u0430_\u0440\u0430\u0431\u043e\u0442\u0430_parsevk_docs_superpowers_specs_2026_05_07_tasks_service_migration_design_\u0440\u0430\u0441\u0441\u043c\u043e\u0442\u0440\u0435\u043d\u043d\u044b\u0435_\u043f\u043e\u0434\u0445\u043e\u0434\u044b", "target": "home_pc051_\u0440\u0430\u0437\u0440\u0430\u0431\u043e\u0442\u043a\u0430_\u0440\u0430\u0431\u043e\u0442\u0430_parsevk_docs_superpowers_specs_2026_05_07_tasks_service_migration_design_\u043f\u043e\u0434\u0445\u043e\u0434_c_\u043f\u0435\u0440\u0435\u043d\u043e\u0441_tasks_\u0438_vk_worker_\u0432\u043c\u0435\u0441\u0442\u0435", "relation": "contains", "confidence": "EXTRACTED", "source_file": "docs/superpowers/specs/2026-05-07-tasks-service-migration-design.md", "source_location": "L67", "weight": 1.0}, {"source": "home_pc051_\u0440\u0430\u0437\u0440\u0430\u0431\u043e\u0442\u043a\u0430_\u0440\u0430\u0431\u043e\u0442\u0430_parsevk_docs_superpowers_specs_2026_05_07_tasks_service_migration_design_tasks_service_migration_design", "target": "home_pc051_\u0440\u0430\u0437\u0440\u0430\u0431\u043e\u0442\u043a\u0430_\u0440\u0430\u0431\u043e\u0442\u0430_parsevk_docs_superpowers_specs_2026_05_07_tasks_service_migration_design_\u0430\u0440\u0445\u0438\u0442\u0435\u043a\u0442\u0443\u0440\u0430", "relation": "contains", "confidence": "EXTRACTED", "source_file": "docs/superpowers/specs/2026-05-07-tasks-service-migration-design.md", "source_location": "L73", "weight": 1.0}, {"source": "home_pc051_\u0440\u0430\u0437\u0440\u0430\u0431\u043e\u0442\u043a\u0430_\u0440\u0430\u0431\u043e\u0442\u0430_parsevk_docs_superpowers_specs_2026_05_07_tasks_service_migration_design_tasks_service_migration_design", "target": "home_pc051_\u0440\u0430\u0437\u0440\u0430\u0431\u043e\u0442\u043a\u0430_\u0440\u0430\u0431\u043e\u0442\u0430_parsevk_docs_superpowers_specs_2026_05_07_tasks_service_migration_design_\u0434\u0430\u043d\u043d\u044b\u0435", "relation": "contains", "confidence": "EXTRACTED", "source_file": "docs/superpowers/specs/2026-05-07-tasks-service-migration-design.md", "source_location": "L120", "weight": 1.0}, {"source": "home_pc051_\u0440\u0430\u0437\u0440\u0430\u0431\u043e\u0442\u043a\u0430_\u0440\u0430\u0431\u043e\u0442\u0430_parsevk_docs_superpowers_specs_2026_05_07_tasks_service_migration_design_\u0434\u0430\u043d\u043d\u044b\u0435", "target": "home_pc051_\u0440\u0430\u0437\u0440\u0430\u0431\u043e\u0442\u043a\u0430_\u0440\u0430\u0431\u043e\u0442\u0430_parsevk_docs_superpowers_specs_2026_05_07_tasks_service_migration_design_tasks", "relation": "contains", "confidence": "EXTRACTED", "source_file": "docs/superpowers/specs/2026-05-07-tasks-service-migration-design.md", "source_location": "L125", "weight": 1.0}, {"source": "home_pc051_\u0440\u0430\u0437\u0440\u0430\u0431\u043e\u0442\u043a\u0430_\u0440\u0430\u0431\u043e\u0442\u0430_parsevk_docs_superpowers_specs_2026_05_07_tasks_service_migration_design_\u0434\u0430\u043d\u043d\u044b\u0435", "target": "home_pc051_\u0440\u0430\u0437\u0440\u0430\u0431\u043e\u0442\u043a\u0430_\u0440\u0430\u0431\u043e\u0442\u0430_parsevk_docs_superpowers_specs_2026_05_07_tasks_service_migration_design_task_audit_logs", "relation": "contains", "confidence": "EXTRACTED", "source_file": "docs/superpowers/specs/2026-05-07-tasks-service-migration-design.md", "source_location": "L183", "weight": 1.0}, {"source": "home_pc051_\u0440\u0430\u0437\u0440\u0430\u0431\u043e\u0442\u043a\u0430_\u0440\u0430\u0431\u043e\u0442\u0430_parsevk_docs_superpowers_specs_2026_05_07_tasks_service_migration_design_\u0434\u0430\u043d\u043d\u044b\u0435", "target": "home_pc051_\u0440\u0430\u0437\u0440\u0430\u0431\u043e\u0442\u043a\u0430_\u0440\u0430\u0431\u043e\u0442\u0430_parsevk_docs_superpowers_specs_2026_05_07_tasks_service_migration_design_task_automation_settings", "relation": "contains", "confidence": "EXTRACTED", "source_file": "docs/superpowers/specs/2026-05-07-tasks-service-migration-design.md", "source_location": "L226", "weight": 1.0}, {"source": "home_pc051_\u0440\u0430\u0437\u0440\u0430\u0431\u043e\u0442\u043a\u0430_\u0440\u0430\u0431\u043e\u0442\u0430_parsevk_docs_superpowers_specs_2026_05_07_tasks_service_migration_design_\u0434\u0430\u043d\u043d\u044b\u0435", "target": "home_pc051_\u0440\u0430\u0437\u0440\u0430\u0431\u043e\u0442\u043a\u0430_\u0440\u0430\u0431\u043e\u0442\u0430_parsevk_docs_superpowers_specs_2026_05_07_tasks_service_migration_design_outbox_events", "relation": "contains", "confidence": "EXTRACTED", "source_file": "docs/superpowers/specs/2026-05-07-tasks-service-migration-design.md", "source_location": "L257", "weight": 1.0}, {"source": "home_pc051_\u0440\u0430\u0437\u0440\u0430\u0431\u043e\u0442\u043a\u0430_\u0440\u0430\u0431\u043e\u0442\u0430_parsevk_docs_superpowers_specs_2026_05_07_tasks_service_migration_design_tasks_service_migration_design", "target": "home_pc051_\u0440\u0430\u0437\u0440\u0430\u0431\u043e\u0442\u043a\u0430_\u0440\u0430\u0431\u043e\u0442\u0430_parsevk_docs_superpowers_specs_2026_05_07_tasks_service_migration_design_api_contract", "relation": "contains", "confidence": "EXTRACTED", "source_file": "docs/superpowers/specs/2026-05-07-tasks-service-migration-design.md", "source_location": "L287", "weight": 1.0}, {"source": "home_pc051_\u0440\u0430\u0437\u0440\u0430\u0431\u043e\u0442\u043a\u0430_\u0440\u0430\u0431\u043e\u0442\u0430_parsevk_docs_superpowers_specs_2026_05_07_tasks_service_migration_design_tasks_service_migration_design", "target": "home_pc051_\u0440\u0430\u0437\u0440\u0430\u0431\u043e\u0442\u043a\u0430_\u0440\u0430\u0431\u043e\u0442\u0430_parsevk_docs_superpowers_specs_2026_05_07_tasks_service_migration_design_behavior", "relation": "contains", "confidence": "EXTRACTED", "source_file": "docs/superpowers/specs/2026-05-07-tasks-service-migration-design.md", "source_location": "L398", "weight": 1.0}, {"source": "home_pc051_\u0440\u0430\u0437\u0440\u0430\u0431\u043e\u0442\u043a\u0430_\u0440\u0430\u0431\u043e\u0442\u0430_parsevk_docs_superpowers_specs_2026_05_07_tasks_service_migration_design_behavior", "target": "home_pc051_\u0440\u0430\u0437\u0440\u0430\u0431\u043e\u0442\u043a\u0430_\u0440\u0430\u0431\u043e\u0442\u0430_parsevk_docs_superpowers_specs_2026_05_07_tasks_service_migration_design_create_parse_task", "relation": "contains", "confidence": "EXTRACTED", "source_file": "docs/superpowers/specs/2026-05-07-tasks-service-migration-design.md", "source_location": "L400", "weight": 1.0}, {"source": "home_pc051_\u0440\u0430\u0437\u0440\u0430\u0431\u043e\u0442\u043a\u0430_\u0440\u0430\u0431\u043e\u0442\u0430_parsevk_docs_superpowers_specs_2026_05_07_tasks_service_migration_design_behavior", "target": "home_pc051_\u0440\u0430\u0437\u0440\u0430\u0431\u043e\u0442\u043a\u0430_\u0440\u0430\u0431\u043e\u0442\u0430_parsevk_docs_superpowers_specs_2026_05_07_tasks_service_migration_design_resume", "relation": "contains", "confidence": "EXTRACTED", "source_file": "docs/superpowers/specs/2026-05-07-tasks-service-migration-design.md", "source_location": "L413", "weight": 1.0}, {"source": "home_pc051_\u0440\u0430\u0437\u0440\u0430\u0431\u043e\u0442\u043a\u0430_\u0440\u0430\u0431\u043e\u0442\u0430_parsevk_docs_superpowers_specs_2026_05_07_tasks_service_migration_design_behavior", "target": "home_pc051_\u0440\u0430\u0437\u0440\u0430\u0431\u043e\u0442\u043a\u0430_\u0440\u0430\u0431\u043e\u0442\u0430_parsevk_docs_superpowers_specs_2026_05_07_tasks_service_migration_design_check", "relation": "contains", "confidence": "EXTRACTED", "source_file": "docs/superpowers/specs/2026-05-07-tasks-service-migration-design.md", "source_location": "L424", "weight": 1.0}, {"source": "home_pc051_\u0440\u0430\u0437\u0440\u0430\u0431\u043e\u0442\u043a\u0430_\u0440\u0430\u0431\u043e\u0442\u0430_parsevk_docs_superpowers_specs_2026_05_07_tasks_service_migration_design_behavior", "target": "home_pc051_\u0440\u0430\u0437\u0440\u0430\u0431\u043e\u0442\u043a\u0430_\u0440\u0430\u0431\u043e\u0442\u0430_parsevk_docs_superpowers_specs_2026_05_07_tasks_service_migration_design_delete", "relation": "contains", "confidence": "EXTRACTED", "source_file": "docs/superpowers/specs/2026-05-07-tasks-service-migration-design.md", "source_location": "L435", "weight": 1.0}, {"source": "home_pc051_\u0440\u0430\u0437\u0440\u0430\u0431\u043e\u0442\u043a\u0430_\u0440\u0430\u0431\u043e\u0442\u0430_parsevk_docs_superpowers_specs_2026_05_07_tasks_service_migration_design_behavior", "target": "home_pc051_\u0440\u0430\u0437\u0440\u0430\u0431\u043e\u0442\u043a\u0430_\u0440\u0430\u0431\u043e\u0442\u0430_parsevk_docs_superpowers_specs_2026_05_07_tasks_service_migration_design_automation_settings", "relation": "contains", "confidence": "EXTRACTED", "source_file": "docs/superpowers/specs/2026-05-07-tasks-service-migration-design.md", "source_location": "L451", "weight": 1.0}, {"source": "home_pc051_\u0440\u0430\u0437\u0440\u0430\u0431\u043e\u0442\u043a\u0430_\u0440\u0430\u0431\u043e\u0442\u0430_parsevk_docs_superpowers_specs_2026_05_07_tasks_service_migration_design_behavior", "target": "home_pc051_\u0440\u0430\u0437\u0440\u0430\u0431\u043e\u0442\u043a\u0430_\u0440\u0430\u0431\u043e\u0442\u0430_parsevk_docs_superpowers_specs_2026_05_07_tasks_service_migration_design_automation_run", "relation": "contains", "confidence": "EXTRACTED", "source_file": "docs/superpowers/specs/2026-05-07-tasks-service-migration-design.md", "source_location": "L494", "weight": 1.0}, {"source": "home_pc051_\u0440\u0430\u0437\u0440\u0430\u0431\u043e\u0442\u043a\u0430_\u0440\u0430\u0431\u043e\u0442\u0430_parsevk_docs_superpowers_specs_2026_05_07_tasks_service_migration_design_tasks_service_migration_design", "target": "home_pc051_\u0440\u0430\u0437\u0440\u0430\u0431\u043e\u0442\u043a\u0430_\u0440\u0430\u0431\u043e\u0442\u0430_parsevk_docs_superpowers_specs_2026_05_07_tasks_service_migration_design_gateway_responsibilities", "relation": "contains", "confidence": "EXTRACTED", "source_file": "docs/superpowers/specs/2026-05-07-tasks-service-migration-design.md", "source_location": "L551", "weight": 1.0}, {"source": "home_pc051_\u0440\u0430\u0437\u0440\u0430\u0431\u043e\u0442\u043a\u0430_\u0440\u0430\u0431\u043e\u0442\u0430_parsevk_docs_superpowers_specs_2026_05_07_tasks_service_migration_design_tasks_service_migration_design", "target": "home_pc051_\u0440\u0430\u0437\u0440\u0430\u0431\u043e\u0442\u043a\u0430_\u0440\u0430\u0431\u043e\u0442\u0430_parsevk_docs_superpowers_specs_2026_05_07_tasks_service_migration_design_frontend_migration", "relation": "contains", "confidence": "EXTRACTED", "source_file": "docs/superpowers/specs/2026-05-07-tasks-service-migration-design.md", "source_location": "L565", "weight": 1.0}, {"source": "home_pc051_\u0440\u0430\u0437\u0440\u0430\u0431\u043e\u0442\u043a\u0430_\u0440\u0430\u0431\u043e\u0442\u0430_parsevk_docs_superpowers_specs_2026_05_07_tasks_service_migration_design_tasks_service_migration_design", "target": "home_pc051_\u0440\u0430\u0437\u0440\u0430\u0431\u043e\u0442\u043a\u0430_\u0440\u0430\u0431\u043e\u0442\u0430_parsevk_docs_superpowers_specs_2026_05_07_tasks_service_migration_design_events", "relation": "contains", "confidence": "EXTRACTED", "source_file": "docs/superpowers/specs/2026-05-07-tasks-service-migration-design.md", "source_location": "L576", "weight": 1.0}, {"source": "home_pc051_\u0440\u0430\u0437\u0440\u0430\u0431\u043e\u0442\u043a\u0430_\u0440\u0430\u0431\u043e\u0442\u0430_parsevk_docs_superpowers_specs_2026_05_07_tasks_service_migration_design_tasks_service_migration_design", "target": "home_pc051_\u0440\u0430\u0437\u0440\u0430\u0431\u043e\u0442\u043a\u0430_\u0440\u0430\u0431\u043e\u0442\u0430_parsevk_docs_superpowers_specs_2026_05_07_tasks_service_migration_design_testing", "relation": "contains", "confidence": "EXTRACTED", "source_file": "docs/superpowers/specs/2026-05-07-tasks-service-migration-design.md", "source_location": "L604", "weight": 1.0}, {"source": "home_pc051_\u0440\u0430\u0437\u0440\u0430\u0431\u043e\u0442\u043a\u0430_\u0440\u0430\u0431\u043e\u0442\u0430_parsevk_docs_superpowers_specs_2026_05_07_tasks_service_migration_design_tasks_service_migration_design", "target": "home_pc051_\u0440\u0430\u0437\u0440\u0430\u0431\u043e\u0442\u043a\u0430_\u0440\u0430\u0431\u043e\u0442\u0430_parsevk_docs_superpowers_specs_2026_05_07_tasks_service_migration_design_rollout", "relation": "contains", "confidence": "EXTRACTED", "source_file": "docs/superpowers/specs/2026-05-07-tasks-service-migration-design.md", "source_location": "L648", "weight": 1.0}, {"source": "home_pc051_\u0440\u0430\u0437\u0440\u0430\u0431\u043e\u0442\u043a\u0430_\u0440\u0430\u0431\u043e\u0442\u0430_parsevk_docs_superpowers_specs_2026_05_07_tasks_service_migration_design_tasks_service_migration_design", "target": "home_pc051_\u0440\u0430\u0437\u0440\u0430\u0431\u043e\u0442\u043a\u0430_\u0440\u0430\u0431\u043e\u0442\u0430_parsevk_docs_superpowers_specs_2026_05_07_tasks_service_migration_design_risks", "relation": "contains", "confidence": "EXTRACTED", "source_file": "docs/superpowers/specs/2026-05-07-tasks-service-migration-design.md", "source_location": "L659", "weight": 1.0}, {"source": "home_pc051_\u0440\u0430\u0437\u0440\u0430\u0431\u043e\u0442\u043a\u0430_\u0440\u0430\u0431\u043e\u0442\u0430_parsevk_docs_superpowers_specs_2026_05_07_tasks_service_migration_design_tasks_service_migration_design", "target": "home_pc051_\u0440\u0430\u0437\u0440\u0430\u0431\u043e\u0442\u043a\u0430_\u0440\u0430\u0431\u043e\u0442\u0430_parsevk_docs_superpowers_specs_2026_05_07_tasks_service_migration_design_resolved_decisions", "relation": "contains", "confidence": "EXTRACTED", "source_file": "docs/superpowers/specs/2026-05-07-tasks-service-migration-design.md", "source_location": "L674", "weight": 1.0}], "input_tokens": 0, "output_tokens": 0}